schlange/__init__.py
schlange/__main__.py
schlange/schlange.py
schlange/background/__init__.py
schlange/background/cleanup_worker.py
schlange/background/execution_worker.py
schlange/background/schedule_worker.py
schlange/background/worker.py
schlange/cli/__init__.py
schlange/cli/app.py
schlange/cli/bench_command.py
schlange/cli/command.py
schlange/cli/data_mapper.py
schlange/cli/main.py
schlange/cli/schedule_command.py
schlange/cli/schedule_delete_command.py
schlange/cli/schedule_inspect_command.py
schlange/cli/schedule_list_command.py
schlange/cli/stress_command.py
schlange/cli/subparsers.py
schlange/cli/task_command.py
schlange/cli/task_create_command.py
schlange/cli/task_delete_command.py
schlange/cli/task_inspect_command.py
schlange/cli/task_list_command.py
schlange/cli/task_reactivate_command.py
schlange/core/__init__.py
schlange/core/aggregate.py
schlange/core/cleanup_policy.py
schlange/core/dto.py
schlange/core/errors.py
schlange/core/retry_policy.py
schlange/core/schedule.py
schlange/core/schedule_firing.py
schlange/core/schedule_repository.py
schlange/core/schedule_service.py
schlange/core/schedule_specification.py
schlange/core/task.py
schlange/core/task_execution.py
schlange/core/task_handler.py
schlange/core/task_repository.py
schlange/core/task_service.py
schlange/core/task_specification.py
schlange/core/task_state.py
schlange/sqlite/__init__.py
schlange/sqlite/connection.py
schlange/sqlite/connection_pool.py
schlange/sqlite/data_mapper.py
schlange/sqlite/database.py
schlange/sqlite/errors.py
schlange/sqlite/schedule_repository.py
schlange/sqlite/task_repository.py
schlange/sqlite/transaction.py
schlange/sqlite/migrations/01_init.sql
schlange/sqlite/migrations/02_add_schedules.sql
schlange_queue-0.1.2.dist-info/METADATA
schlange_queue-0.1.2.dist-info/WHEEL
schlange_queue-0.1.2.dist-info/top_level.txt
schlange_queue-0.1.2.dist-info/RECORD
